tests/__init__.py
tests/settings.py
tests/urls.py
twitter_oauth_ios/__init__.py
twitter_oauth_ios/admin.py
twitter_oauth_ios/apps.py
twitter_oauth_ios/forms.py
twitter_oauth_ios/urls.py
twitter_oauth_ios/utils.py
twitter_oauth_ios/views.py
twitter_oauth_ios/migrations/__init__.py
twitter_oauth_ios/tests/__init__.py
twitter_oauth_ios/tests/test_forms.py
twitter_oauth_ios/tests/test_runner.py
twitter_oauth_ios/tests/test_urls.py
twitter_oauth_ios/tests/test_views.py
twitter_oauth_ios_django-1.0.3.dist-info/METADATA
twitter_oauth_ios_django-1.0.3.dist-info/RECORD
twitter_oauth_ios_django-1.0.3.dist-info/WHEEL
twitter_oauth_ios_django-1.0.3.dist-info/top_level.txt
