Metadata-Version: 2.1
Name: twitter-oauth-ios-django
Version: 1.0.3
Summary: Create UserSocialAuth of social_django with OAuth login with twitter-kit-ios.
Home-page: https://github.com/nnsnodnb/twitter-oauth-django
Author: nnsnodnb
Author-email: ahr63_gej@me.com
License: MIT
Download-URL: https://github.com/nnsnodnb/twitter-oauth-django/tarball/master
Platform: UNKNOWN
Classifier: Environment :: Web Environment
Classifier: Framework :: Django
Classifier: Intended Audience :: Developers
Classifier: License :: OSI Approved :: MIT License
Classifier: Programming Language :: Python
Classifier: Programming Language :: Python :: 3
Classifier: Programming Language :: Python :: 3 :: Only
Classifier: Programming Language :: Python :: 3.4
Classifier: Programming Language :: Python :: 3.5
Classifier: Programming Language :: Python :: 3.6
Classifier: Topic :: Internet :: WWW/HTTP
Classifier: Topic :: Software Development :: Libraries :: Application Frameworks
Classifier: Topic :: Software Development :: Libraries :: Python Modules
Requires-Dist: Django (>=2.0)
Requires-Dist: social-auth-app-django (>=2.1.0)
Requires-Dist: requests-oauthlib (>=0.8.0)
